{
  "$schema": "https://developer.microsoft.com/json-schemas/fabric/item/report/definition/visualContainer/2.1.0/schema.json",
  "name": "73b75c90383d08262c31",
  "position": {
    "x": 197.65786452353618,
    "y": 476.142365097589,
    "z": 6000,
    "height": 243.94948335246843,
    "width": 575.33869115958669,
    "tabOrder": 5000
  },
  "visual": {
    "visualType": "map",
    "query": {
      "queryState": {
        "Category": {
          "projections": [
            {
              "field": {
                "Column": {
                  "Expression": {
                    "SourceRef": {
                      "Entity": "Stores"
                    }
                  },
                  "Property": "store_city"
                }
              },
              "queryRef": "Stores.store_city",
              "nativeQueryRef": "store_city",
              "active": true
            }
          ]
        },
        "Tooltips": {
          "projections": [
            {
              "field": {
                "Measure": {
                  "Expression": {
                    "SourceRef": {
                      "Entity": "Transaction_Data"
                    }
                  },
                  "Property": "Total Transactions"
                }
              },
              "queryRef": "Transaction_Data.Total Transactions",
              "nativeQueryRef": "Total Transactions"
            }
          ]
        }
      }
    },
    "objects": {
      "bubbles": [
        {
          "properties": {
            "bubbleSize": {
              "expr": {
                "Literal": {
                  "Value": "10L"
                }
              }
            }
          }
        }
      ],
      "dataPoint": [
        {
          "properties": {
            "fill": {
              "solid": {
                "color": {
                  "expr": {
                    "Literal": {
                      "Value": "'#017E1E'"
                    }
                  }
                }
              }
            }
          }
        }
      ]
    },
    "visualContainerObjects": {
      "title": [
        {
          "properties": {
            "show": {
              "expr": {
                "Literal": {
                  "Value": "false"
                }
              }
            }
          }
        }
      ]
    },
    "drillFilterOtherVisuals": true
  }
}